pysoserial.py
pysoserial-1.0.1.dist-info/METADATA
pysoserial-1.0.1.dist-info/WHEEL
pysoserial-1.0.1.dist-info/entry_points.txt
pysoserial-1.0.1.dist-info/top_level.txt
pysoserial-1.0.1.dist-info/RECORD
